moodle_mcp/__init__.py
moodle_mcp/api.py
moodle_mcp/logger.py
moodle_mcp/moodle.py
moodle_mcp/server.py
moodle_mcp/utils.py
mseep_moodle_mcp-0.1.4.dist-info/METADATA
mseep_moodle_mcp-0.1.4.dist-info/WHEEL
mseep_moodle_mcp-0.1.4.dist-info/entry_points.txt
mseep_moodle_mcp-0.1.4.dist-info/top_level.txt
mseep_moodle_mcp-0.1.4.dist-info/RECORD
