Metadata-Version: 2.4
Name: mseep-moodle-mcp
Version: 0.1.4
Summary: A Model Context Protocol (MCP) server implementation that provides capabilities to interact with Moodle LMS.
Author-email: mseep <support@skydeck.ai>
Project-URL: Homepage, https://github.com/loyaniu/moodle-mcp
Requires-Python: >=3.10
Requires-Dist: glom>=24.11.0
Requires-Dist: mcp[cli]>=1.6.0
Requires-Dist: python-dotenv>=1.1.0
Requires-Dist: requests>=2.32.3
